simpleetl/__init__.py
simpleetl/_functions/__init__.py
simpleetl/_functions/_datatypefuncs.py
simpleetl/_functions/_datatypes.py
simpleetl/_functions/_db_get_nextid.py
simpleetl/_functions/_db_quoting.py
simpleetl/_functions/_db_schema_handler.py
simpleetl/_functions/_db_tables.py
simpleetl/_functions/_db_tables_scd.py
simpleetl/_functions/_dbfunctions.py
simpleetl/_modules/Batchlog.py
simpleetl/_modules/Configuration.py
simpleetl/_modules/Datatype.py
simpleetl/_modules/Dimension.py
simpleetl/_modules/FactTable.py
simpleetl/_modules/Logger.py
simpleetl/_modules/PostgresLoggingHandler.py
simpleetl/_modules/__init__.py
simpleetl/_processing/ETLProcess.py
simpleetl/_processing/Postprocess.py
simpleetl/_processing/Transform.py
simpleetl/_processing/__init__.py
simpleetl/_processing/runetl.py
simpleetl-1.1.0.dist-info/LICENSE
simpleetl-1.1.0.dist-info/METADATA
simpleetl-1.1.0.dist-info/WHEEL
simpleetl-1.1.0.dist-info/top_level.txt
simpleetl-1.1.0.dist-info/RECORD
