Metadata-Version: 2.1
Name: simpleetl
Version: 1.1.0
Summary: SimpleETL - ETL Processing by Simple Specifications
Home-page: https://bitbucket.org/IngridBroe/simpleetl/
Author: FlexDanmark
Author-email: ibr@flexdanmark.dk
License: UNKNOWN
Project-URL: Packaging tutorial, https://packaging.python.org/tutorials/distributing-packages/
Project-URL: simpleetl documentation, https://bitbucket.org/IngridBroe/simpleetl/
Project-URL: simpleetl source, https://bitbucket.org/IngridBroe/simpleetl/
Platform: UNKNOWN
Classifier: Development Status :: 5 - Production/Stable
Classifier: Intended Audience :: Developers
Classifier: License :: OSI Approved :: BSD License
Classifier: Programming Language :: Python
Classifier: Programming Language :: Python :: 3
Classifier: Topic :: Database
Classifier: Topic :: Database :: Front-Ends
Classifier: Topic :: Software Development
Classifier: Topic :: Software Development :: Libraries :: Python Modules
Classifier: Topic :: Software Development :: Libraries :: Application Frameworks
Requires-Python: >=3
License-File: LICENSE
Requires-Dist: pygrametl (>=2.6)
Requires-Dist: psycopg2-binary (>=2.8.6)
